[{"title": "Flutterアプリ開発", "stack": ["Flutter", "Dart", "Firebase", "Riverpod", "Dio"], "blurb": "UI/UX設計からFirebase認証・通知連携、CI自動ビルドまで──iOS/Android両対応アプリをワンストップで開発します。"}, {"title": "バックエンド / API開発（Rails）", "stack": ["Ruby on Rails", "PostgreSQL", "SendGrid", "Firebase Admin SDK"], "blurb": "RESTful API設計・認証・招待コード登録・メール通知をセキュアかつ拡張性の高い構成で実装します。"}, {"title": "DevOps / インフラ構築", "stack": ["GitHub Actions", "Docker", "AWS", "Cloudflare"], "blurb": "テスト・ビルド自動化からBot対策／レートリミット設定まで、本番運用に耐えるCI/CD・運用基盤を構築します。"}, {"title": "フロントエンド開発（Web）", "stack": ["Vue 3", "TypeScript", "Nuxt 3", "React", "Vite", "Tailwind CSS"], "blurb": "モダンフレームワークでアクセシビリティと保守性を両立したSPAやポートフォリオサイトをデザイン・実装します。"}, {"title": "Web / デスクトップアプリ開発", "stack": ["Django", "Flask", "Streamlit", "C# (.NET)", "Electron", "WPF/Prism"], "blurb": "Python系WebアプリからWindowsデスクトップアプリまで、業務効率化ツールを高速に開発します。"}]